ros2_simple_pub/__init__.py
ros2_simple_pub/publisher.py
ros2_simple_pub-0.1.0.dist-info/METADATA
ros2_simple_pub-0.1.0.dist-info/WHEEL
ros2_simple_pub-0.1.0.dist-info/top_level.txt
ros2_simple_pub-0.1.0.dist-info/RECORD
