Metadata-Version: 2.4
Name: ros2_simple_pub
Version: 0.1.0
Summary: A simple configurable ROS2 publisher
Author: Akshay
Author-email: akshayfusion1@gmail.com
Requires-Python: >=3.7
Dynamic: author
Dynamic: author-email
Dynamic: description
Dynamic: description-content-type
Dynamic: requires-python
Dynamic: summary
